poetry_kit/__init__.py
poetry_kit/__itinerary/later.S.HTML
poetry_kit/_clique/__init__.py
poetry_kit/_clique/group/__init__.py
poetry_kit/_licenses/gpl-3.0-standalone.html
poetry_kit/_status/DB/records.json
poetry_kit/_status/monitors/status_1.py
poetry_kit/_status/status.proc.py
poetry_kit/license.S.HTML
poetry_kit/mixer.MD
poetry_kit/mixer.S.HTML
poetry_kit-0.1.6.dist-info/METADATA
poetry_kit-0.1.6.dist-info/WHEEL
poetry_kit-0.1.6.dist-info/entry_points.txt
poetry_kit-0.1.6.dist-info/RECORD
